exman/__init__.py
exman/index.py
exman/parser.py
exman-0.1.9.data/scripts/exman
exman-0.1.9.dist-info/METADATA
exman-0.1.9.dist-info/WHEEL
exman-0.1.9.dist-info/top_level.txt
exman-0.1.9.dist-info/RECORD
