Metadata-Version: 2.1
Name: exman
Version: 0.1.9
Summary: Simple and minimalistic utility to manage many experiments runs and custom analysis of results
Home-page: UNKNOWN
Author: Max Kochurov
Author-email: maxim.v.kochurov@gmail.com
License: UNKNOWN
Platform: UNKNOWN
Requires-Python: >=3.6
Requires-Dist: configargparse (>=0.14.0)
Requires-Dist: PyYAML
Requires-Dist: strconv
Requires-Dist: pandas
Requires-Dist: filelock
Requires-Dist: inputimeout
Requires-Dist: joblib
Requires-Dist: gitpython
